Metadata-Version: 2.4
Name: nDTomo
Version: 2026.1
Summary: nDTomo software suite
Author-email: "A. Vamvakeros" <antonyvam@gmail.com>
Project-URL: Homepage, http://github.com/antonyvam/nDTomo
Classifier: Intended Audience :: Science/Research
Classifier: Topic :: Scientific/Engineering
Classifier: Topic :: Scientific/Engineering :: Chemistry
Classifier: Topic :: Scientific/Engineering :: Visualization
Requires-Python: >=3.9
License-File: LICENSE
Requires-Dist: h5py
Requires-Dist: matplotlib
Requires-Dist: numpy
Requires-Dist: scipy
Requires-Dist: siphash24
Requires-Dist: pyqtgraph
Requires-Dist: scikit-image
Requires-Dist: scikit-learn
Requires-Dist: xdesign
Requires-Dist: tqdm
Requires-Dist: ipykernel
Requires-Dist: pystackreg
Requires-Dist: tifffile
Requires-Dist: jupyterlab
Requires-Dist: algotom
Requires-Dist: fabio
Requires-Dist: pyFAI>=2025.01
Requires-Dist: napari
Requires-Dist: configobj
Requires-Dist: ipympl
Requires-Dist: pyqt5
Requires-Dist: pyopencl
Requires-Dist: jupyterlab_widgets
Provides-Extra: torch
Requires-Dist: torch; extra == "torch"
Requires-Dist: torchvision; extra == "torch"
Requires-Dist: torchaudio; extra == "torch"
Dynamic: license-file
